gaia_var/__init__.py
gaia_var/archive.py
gaia_var/event.py
gaia_var/gaps.py
gaia_var/preprocess.py
gaia_var-0.9.3.dist-info/METADATA
gaia_var-0.9.3.dist-info/WHEEL
gaia_var-0.9.3.dist-info/top_level.txt
gaia_var-0.9.3.dist-info/RECORD
